{"stats": {"team_a": "Como", "team_b": "Juventus", "team_a_canonical": "Como", "team_b_canonical": "Juventus", "total_matches": 6, "team_a_wins": 2, "team_b_wins": 3, "draws": 1, "team_a_goals_for": 7, "team_a_goals_against": 9, "team_b_goals_for": 9, "team_b_goals_against": 7, "team_a_avg_goals_for": 1.1666666666666667, "team_a_avg_goals_against": 1.5, "team_b_avg_goals_for": 1.5, "team_b_avg_goals_against": 1.1666666666666667, "last_updated": "2026-02-15 20:09:57.011630"}, "recent_matches": [{"utc_date": "2025-10-19", "home_team": "Como", "away_team": "Juventus", "home_goals": 2, "away_goals": 0}, {"utc_date": "2025-10-19", "home_team": "Como", "away_team": "Juventus", "home_goals": 2, "away_goals": 0}, {"utc_date": "2025-02-07", "home_team": "Como", "away_team": "Juventus", "home_goals": 1, "away_goals": 2}, {"utc_date": "2024-08-19", "home_team": "Juventus", "away_team": "Como", "home_goals": 3, "away_goals": 0}, {"utc_date": "2003-02-22", "home_team": "Como", "away_team": "Juventus", "home_goals": 1, "away_goals": 3}, {"utc_date": "2002-10-06", "home_team": "Juventus", "away_team": "Como", "home_goals": 1, "away_goals": 1}]}