{"match_id": 783876629281123597, "home_team": "PSV Eindhoven", "away_team": "Nijmegen", "competition": "DED", "experts": {"elo": {"probs": {"home": 0.186, "draw": 0.284, "away": 0.529}, "confidence": 1.0, "features": {"elo_home": 1678.872, "elo_away": 1931.097, "elo_diff": -252.225, "elo_home_adv": 71.0, "elo_momentum_h": 3.298, "elo_momentum_a": 0.235, "elo_volatility_h": 8.911, "elo_volatility_a": 5.911, "elo_tanh_diff": -0.558, "elo_log_diff": -5.534, "elo_weighted_mom_h": 3.298, "elo_weighted_mom_a": 0.235}}, "glicko2": {"probs": {"home": 0.189, "draw": 0.295, "away": 0.516}, "confidence": 0.767, "features": {"glicko2_rating_h": 2465.989, "glicko2_rating_a": 2769.479, "glicko2_rd_h": 105.141, "glicko2_rd_a": 104.225, "glicko2_volatility_h": 460.533, "glicko2_volatility_a": 42.714, "glicko2_rating_diff": -303.49, "glicko2_home_adv": 52.0}}, "pi_rating": {"probs": {"home": 0.375, "draw": 0.245, "away": 0.38}, "confidence": 1.0, "features": {"pi_home_rating_h": 1507.437, "pi_away_rating_h": 1482.369, "pi_away_rating_a": 1512.905, "pi_home_rating_a": 1541.968, "pi_expected_gd": -0.009, "pi_rating_diff": -5.468}}, "network": {"probs": {"home": 0.333, "draw": 0.333, "away": 0.333}, "confidence": 0.0, "features": {"net_pr_h": 0.0, "net_pr_a": 0.0, "net_pr_diff": 0.0, "net_ma_h": 0.0, "net_ma_a": 0.0, "net_ma_diff": 0.0, "net_co_h": 0.0, "net_co_a": 0.0, "net_co_diff": 0.0, "net_composite_diff": 0.0, "net_agreement": 0.0}}, "kalman_elo": {"probs": {"home": 0.402, "draw": 0.303, "away": 0.295}, "confidence": 0.918, "features": {"kalman_strength_h": -0.874, "kalman_strength_a": -0.421, "kalman_diff": -0.454, "kalman_uncertainty_h": 0.082, "kalman_uncertainty_a": 0.082, "kalman_gain": 0.328}}, "bayesian_rate": {"probs": {"home": 0.388, "draw": 0.177, "away": 0.435}, "confidence": 1.0, "features": {"bayes_wr_h": 0.42, "bayes_wr_a": 0.487, "bayes_cs_h": 0.32, "bayes_cs_a": 0.32, "bayes_btts_h": 0.567, "bayes_btts_a": 0.567, "bayes_o25_h": 0.567, "bayes_o25_a": 0.5, "bayes_sf_h": 0.7, "bayes_sf_a": 0.767, "bayes_gpm_h": 1.393, "bayes_gpm_a": 1.567, "bayes_home_wr": 0.367, "bayes_away_wr": 0.4, "bayes_wr_diff": -0.067, "bayes_cs_diff": 0.0, "bayes_gpm_diff": -0.174, "bayes_gpm_sum": 2.961}}, "bayesian_ss": {"probs": {"home": 0.082, "draw": 0.836, "away": 0.082}, "confidence": 0.817, "features": {"bss_lambda_h": 0.1, "bss_lambda_a": 0.1, "bss_confidence": 0.817, "bss_rs_gamma": -0.017, "bss_zero_infl": 0.05, "bss_momentum_h": -0.009, "bss_momentum_a": 0.158, "bss_attack_h": -1.454, "bss_attack_a": -1.176, "bss_defense_h": 2.0, "bss_defense_a": 2.0}}, "poisson": {"probs": {"home": 0.214, "draw": 0.211, "away": 0.575}, "confidence": 1.0, "features": {"pois_lambda_h": 1.177, "pois_lambda_a": 2.049, "pois_lambda_diff": -0.872, "pois_lambda_sum": 3.226, "pois_lambda_prod": 2.411, "pois_btts": 0.603, "pois_o25": 0.625, "pois_o15": 0.832, "pois_u25": 0.375, "pois_cs00": 0.04, "pois_zero_h": 0.308, "pois_zero_a": 0.129, "pois_ml_hg": 1.0, "pois_ml_ag": 2.0, "pois_skew": -0.136, "pois_dc_ph": 0.21, "pois_dc_pd": 0.219, "pois_dc_pa": 0.571, "pois_dc_cs00": 0.044, "pois_dc_btts": 0.607, "pois_sk_mean_gd": -0.872, "pois_sk_var_gd": 3.226, "pois_sk_skew": -0.15, "pois_mc_ph": 0.212, "pois_mc_pd": 0.207, "pois_mc_pa": 0.581, "pois_mc_btts": 0.606, "pois_mc_o25": 0.629, "pois_mc_o35": 0.39, "pois_mc_var_total": 3.309, "pois_bp_ph": 0.212, "pois_bp_pd": 0.213, "pois_bp_btts": 0.603, "pois_bp_o25": 0.624, "pois_cop_ph": 0.223, "pois_cop_pd": 0.204, "pois_cop_btts": 0.598, "pois_cop_o25": 0.633, "pois_cmp_ph": 0.211, "pois_cmp_disp_h": 1.039, "pois_cmp_disp_a": 1.04, "pois_bt_ph": 0.424, "pois_bt_pd": 0.11, "pois_bt_pa": 0.466}}, "negbin": {"probs": {"home": 0.162, "draw": 0.197, "away": 0.641}, "confidence": 1.0, "features": {"nb_lambda_h": 0.967, "nb_lambda_a": 2.153, "nb_lambda_diff": -1.186, "nb_r_param": 50.0, "nb_overdispersion": 0.02, "nb_btts": 0.541, "nb_o25": 0.599, "nb_cs00": 0.047}}, "zip_model": {"probs": {"home": 0.195, "draw": 0.301, "away": 0.504}, "confidence": 0.6, "features": {"zip_ph": 0.195, "zip_pd": 0.301, "zip_pa": 0.504, "zip_btts": 0.315, "zip_o25": 0.296, "zip_pi": 0.073, "zip_lam_h": 0.663, "zip_lam_a": 1.346, "zip_kalman_atk_h": 1.268, "zip_kalman_atk_a": 1.811, "zip_kalman_def_h": 1.487, "zip_kalman_def_a": 1.018, "zip_kalman_var_h": 0.4, "zip_kalman_var_a": 0.4}}, "copula": {"probs": {"home": 0.23, "draw": 0.188, "away": 0.581}, "confidence": 1.0, "features": {"cop_frank_home": 0.23, "cop_frank_draw": 0.188, "cop_frank_away": 0.581, "cop_frank_theta": -1.8, "cop_frank_primary": 1.0, "cop_clayton_home": 0.163, "cop_clayton_draw": 0.246, "cop_clayton_away": 0.591, "cop_gumbel_home": 0.161, "cop_gumbel_draw": 0.235, "cop_gumbel_away": 0.605, "cop_avg_ph": 0.185, "cop_avg_pd": 0.223, "cop_avg_pa": 0.592, "cop_lambda_h": 1.037, "cop_lambda_a": 1.974, "cop_p00": 0.027, "cop_btts": 0.534, "cop_o25": 0.606, "cop_entropy": 0.968, "cop_model_spread": 0.032}}, "weibull": {"probs": {"home": 0.194, "draw": 0.214, "away": 0.592}, "confidence": 1.0, "features": {"weib_lambda_h": 1.037, "weib_lambda_a": 1.974, "weib_c_h": 1.081, "weib_c_a": 1.038, "weib_p00": 0.049, "weib_btts": 0.555, "weib_o25": 0.581, "weib_entropy": 0.958, "weib_most_likely_h": 1.0, "weib_most_likely_a": 1.0}}, "double_poisson": {"probs": {"home": 0.151, "draw": 0.107, "away": 0.742}, "confidence": 1.0, "features": {"dpois_lambda_h": 1.037, "dpois_lambda_a": 1.974, "dpois_phi_h": 1.03, "dpois_phi_a": 1.192, "dpois_p00": 0.0, "dpois_btts": 0.939, "dpois_o25": 0.987, "dpois_entropy": 0.746, "dpois_most_likely_h": 2.0, "dpois_most_likely_a": 5.0}}, "skellam_regression": {"probs": {"home": 0.254, "draw": 0.209, "away": 0.537}, "confidence": 1.0, "features": {"skr_mean_gd": -0.707, "skr_var_gd": 3.535, "skr_skewness": -0.106, "skr_lambda_h": 1.414, "skr_lambda_a": 2.121, "skr_lambda_diff": -0.707}}, "ordered_probit": {"probs": {"home": 0.21, "draw": 0.13, "away": 0.66}, "confidence": 0.324, "features": {"op_latent": -0.363, "op_c1": 0.05, "op_c2": 0.444, "op_draw_width": 0.394}}, "market": {"probs": {"home": 0.195, "draw": 0.214, "away": 0.591}, "confidence": 1.0, "features": {"mkt_overround": 0.048, "mkt_src_quality": 4.0, "mkt_has_odds": 1.0, "mkt_using_closing": 1.0, "mkt_move_h": -0.019, "mkt_move_d": 0.001, "mkt_move_a": 0.019, "mkt_has_move": 1.0, "mkt_ou25": 0.617, "mkt_ou_over": 0.066, "mkt_has_ou": 1.0, "mkt_open_ph": 0.214, "mkt_open_pd": 0.214, "mkt_open_pa": 0.572, "mkt_has_open": 1.0, "mkt_logit_h": -1.42, "mkt_logit_d": -1.298, "mkt_logit_a": 0.368, "mkt_entropy": 0.96, "mkt_pin_ph": 0.0, "mkt_pin_pd": 0.0, "mkt_pin_pa": 0.0, "mkt_has_pin": 0.0, "mkt_ah_line": 0.0, "mkt_ah_home": 0.0, "mkt_ah_away": 0.0, "mkt_has_ah": 0.0, "mkt_btts_yes": 0.0, "mkt_btts_no": 0.0, "mkt_btts_implied": 0.0, "mkt_has_btts": 0.0}}, "market_value": {"probs": {"home": 0.333, "draw": 0.333, "away": 0.333}, "confidence": 0.0, "features": {"mv_value_ratio": 0.0, "mv_value_diff_log": 0.0, "mv_avg_value_ratio": 0.0, "mv_depth_diff": 0.0, "mv_age_diff": 0.0, "mv_has_data": 0.0, "mv_home_stronger": 0.0, "mv_value_dominance": 0.0}}, "form": {"probs": {"home": 0.182, "draw": 0.204, "away": 0.614}, "confidence": 1.0, "features": {"form_gf_h": 1.2, "form_ga_h": 2.0, "form_pts_h": 1.4, "form_gf_a": 1.6, "form_ga_a": 1.0, "form_pts_a": 2.2, "form_sh_h": 8.0, "form_sot_h": 2.0, "form_cor_h": 3.8, "form_card_h": 1.4, "form_sh_a": 10.0, "form_sot_a": 3.8, "form_cor_a": 2.8, "form_card_a": 1.0, "form_oaf_h": 1.549, "form_oaf_a": 2.618, "form_home_ppg_h": 1.4, "form_away_ppg_a": 2.6, "form_cs_h": 0.6, "form_cs_a": 0.4, "form_btts_h": 0.4, "form_btts_a": 0.6, "form_momentum_h": 0.667, "form_momentum_a": -0.667, "form_streak_h": 2.0, "form_streak_a": 0.0, "form_gsup_h": -0.8, "form_gsup_a": 0.6, "form_sotr_h": 0.25, "form_sotr_a": 0.38, "form_shrunk_wr_h": 0.346, "form_shrunk_wr_a": 0.578, "form_shrunk_cs_h": 0.249, "form_shrunk_cs_a": 0.374, "form_shrunk_btts_h": 0.539, "form_shrunk_btts_a": 0.497, "form_sched_diff_h": 1811.044, "form_sched_diff_a": 1701.16, "form_conversion_h": 0.706, "form_conversion_a": 0.645, "form_hf_gf_h": 1.0, "form_hf_ga_h": 0.6, "form_af_gf_a": 1.6, "form_af_ga_a": 0.8, "form_hf_sot_h": 2.2, "form_af_sot_a": 3.0, "form_hf_conv_h": 0.455, "form_af_conv_a": 0.533, "form_hf_cs_h": 0.4, "form_af_cs_a": 0.4, "form_decay_ppg_h": 1.926, "form_decay_ppg_a": 1.774, "form_xg_h": 0.0, "form_xg_a": 0.0, "form_xg_diff_h": 0.0, "form_xg_diff_a": 0.0, "form_vs_top_h": 1.25, "form_vs_top_a": 2.6, "form_poss_h": 50.0, "form_poss_a": 50.0, "form_poss_eff_h": 1.2, "form_poss_eff_a": 1.6, "form_poss_dom_h": 0.0, "form_poss_dom_a": 0.0}}, "h2h": {"probs": {"home": 0.231, "draw": 0.174, "away": 0.595}, "confidence": 0.709, "features": {"h2h_n": 24.0, "h2h_pts_h": 0.054, "h2h_pts_a": 2.898, "h2h_gd": -2.462, "h2h_gf_h": 0.515, "h2h_ga_h": 2.978, "h2h_venue_n": 8.0, "h2h_venue_pts": 0.25, "h2h_venue_gd": -2.25, "h2h_venue_wr_h": 0.0, "h2h_venue_gf": 0.75, "h2h_venue_ga": 3.0, "h2h_bogey": 1.0, "h2h_surprise_rate": 0.854, "h2h_dominance": -0.708, "h2h_quality_pts_h": 0.059, "h2h_quality_pts_a": 2.887, "h2h_trend": -0.429, "h2h_goal_vol": 1.518}}, "momentum": {"probs": {"home": 0.504, "draw": 0.201, "away": 0.295}, "confidence": 1.0, "features": {"mom_ema_cross_h": 0.761, "mom_ema_cross_a": -0.71, "mom_ema_cross_diff": 1.471, "mom_gf_slope_h": -0.048, "mom_gf_slope_a": -0.097, "mom_ga_slope_h": 0.194, "mom_ga_slope_a": 0.097, "mom_pts_slope_h": -0.048, "mom_pts_slope_a": -0.194, "mom_pts_slope_diff": 0.145, "mom_vol_h": 1.2, "mom_vol_a": 0.8, "mom_vol_diff": 0.4, "mom_regress_h": 0.933, "mom_regress_a": -0.467, "mom_burst_h": 0.333, "mom_burst_a": -0.333, "mom_drought_h": 0.0, "mom_drought_a": 0.0, "mom_def_tighten_h": -0.267, "mom_def_tighten_a": -0.933, "mom_venue_ema_h": 0.01, "mom_venue_ema_a": 0.813, "mom_venue_gf_slope_h": -0.194, "mom_venue_gf_slope_a": 0.194, "mom_quality_h": 0.829, "mom_quality_a": -0.965, "mom_quality_diff": 1.794, "mom_streak_h": 2.0, "mom_streak_a": 0.0}}, "momentum_indicators": {"probs": {"home": 0.251, "draw": 0.333, "away": 0.415}, "confidence": 1.0, "features": {"mind_home_rsi": 52.136, "mind_away_rsi": 66.154, "mind_home_macd": 0.043, "mind_away_macd": 0.042, "mind_home_macd_signal": 0.049, "mind_away_macd_signal": 0.024, "mind_home_macd_hist": -0.006, "mind_away_macd_hist": 0.018, "mind_home_bb_position": 0.453, "mind_away_bb_position": 0.023, "mind_rsi_divergence": -14.019, "mind_momentum_agreement": 1.0}}, "goal_pattern": {"probs": {"home": 0.316, "draw": 0.198, "away": 0.486}, "confidence": 1.0, "features": {"gp_first_goal_h": 0.54, "gp_first_goal_a": 0.717, "gp_comeback_h": 0.0, "gp_comeback_a": 0.0, "gp_ht_frac_h": 0.233, "gp_ht_frac_a": 0.367, "gp_ht_conc_h": 0.04, "gp_ht_conc_a": 0.067, "gp_fg_win_h": 0.583, "gp_fg_win_a": 0.667, "gp_multi_h": 0.6, "gp_multi_a": 0.8, "gp_nil_h": 0.133, "gp_nil_a": 0.067, "gp_lead_hold_h": 0.75, "gp_lead_hold_a": 0.667, "gp_late_goal_h": 0.731, "gp_late_goal_a": 0.607, "gp_venue_fg_h": 0.55, "gp_venue_fg_a": 0.505, "gp_fg_vs_top_h": 0.504, "gp_fg_vs_top_a": 0.708, "gp_cs_vs_top_h": 0.308, "gp_cs_vs_top_a": 0.308, "gp_cb_vs_top_h": 0.0, "gp_cb_vs_top_a": 0.0}}, "context": {"probs": {"home": 0.452, "draw": 0.28, "away": 0.268}, "confidence": 0.65, "features": {"ctx_rest_h": 0.833, "ctx_rest_a": 0.833, "ctx_rest_diff": 0.0, "ctx_rest_ratio": 1.0, "ctx_short_rest_h": 1.0, "ctx_short_rest_a": 1.0, "ctx_cong7_h": 1.0, "ctx_cong7_a": 1.0, "ctx_cong14_h": 3.0, "ctx_cong14_a": 3.0, "ctx_cong30_h": 7.0, "ctx_cong30_a": 7.0, "ctx_cong7_diff": 0.0, "ctx_cong14_diff": 0.0, "ctx_fatigue_h": 1.2, "ctx_fatigue_a": 1.2, "ctx_fatigue_diff": 0.0, "ctx_midweek_turn_h": 0.0, "ctx_midweek_turn_a": 0.0, "ctx_season_prog": 0.7, "ctx_is_early": 0.0, "ctx_is_late": 0.0, "ctx_dow": 5.0, "ctx_is_weekend": 1.0, "ctx_is_midweek": 0.0, "ctx_hour_utc": 20.0, "ctx_motivation_h": 0.6, "ctx_motivation_a": -0.1, "ctx_motivation_diff": 0.7, "ctx_is_relegation_h": 1.0, "ctx_is_relegation_a": 0.0, "ctx_is_title_race_h": 0.0, "ctx_is_title_race_a": 0.0, "ctx_is_euro_push_h": 0.0, "ctx_is_euro_push_a": 0.0, "ctx_is_safe_h": 0.0, "ctx_is_safe_a": 0.0, "ctx_is_derby": 0.6, "ctx_high_stakes": 0.6}}, "motivation": {"probs": {"home": 0.459, "draw": 0.295, "away": 0.246}, "confidence": 1.0, "features": {"mot_home_objective": 0.0, "mot_away_objective": 1.0, "mot_home_motivation": 1.0, "mot_away_motivation": 0.476, "mot_motivation_diff": 0.524, "mot_season_progress": 0.951, "mot_home_pts_to_obj": 0.0, "mot_away_pts_to_obj": 0.0, "mot_both_high": 0.0, "mot_pressure_diff": 0.6}}, "squad_rotation": {"probs": {"home": 0.333, "draw": 0.333, "away": 0.333}, "confidence": 1.0, "features": {"rot_home_days_rest": 10.021, "rot_away_days_rest": 10.021, "rot_home_matches_7d": 0.0, "rot_away_matches_7d": 0.0, "rot_home_matches_30d": 6.0, "rot_away_matches_30d": 6.0, "rot_home_congestion": 0.05, "rot_away_congestion": 0.05, "rot_congestion_diff": 0.0, "rot_home_fatigue_impact": 0.0, "rot_away_fatigue_impact": 0.0, "rot_rest_advantage": 0.0}}, "injury": {"probs": {"home": 0.321, "draw": 0.334, "away": 0.345}, "confidence": 0.3, "features": {"inj_score_h": 0.415, "inj_score_a": 0.237, "inj_squad_str_h": 0.872, "inj_squad_str_a": 0.958, "inj_injured_h": 17.0, "inj_injured_a": 9.0, "inj_doubtful_h": 0.0, "inj_doubtful_a": 0.0, "inj_suspended_h": 0.0, "inj_suspended_a": 0.0, "inj_fdr_h": 2.667, "inj_fdr_a": 3.333, "inj_fdr6_h": 3.333, "inj_fdr6_a": 3.167, "inj_fdr_future_diff": 0.167, "inj_af_h": 0.0, "inj_af_a": 0.0, "inj_diff": 0.178, "inj_squad_diff": -0.086, "inj_unavailable_h": 17.0, "inj_unavailable_a": 9.0}}, "weather": {"probs": {"home": 0.333, "draw": 0.333, "away": 0.333}, "confidence": 0.0, "features": {"wx_temp_c": NaN, "wx_precip_mm": NaN, "wx_wind_kmh": NaN, "wx_gusts_kmh": NaN, "wx_humidity_pct": NaN, "wx_cloud_cover_pct": NaN, "wx_rain_24h_mm": NaN, "wx_rain_48h_mm": NaN, "wx_extreme_temp": 0.0, "wx_bad_weather": 0.0, "wx_pitch_heavy": 0.0}}, "referee": {"probs": {"home": 0.333, "draw": 0.333, "away": 0.333}, "confidence": 0.0, "features": {"ref_yellow_rate": 0.0, "ref_red_rate": 0.0, "ref_penalty_rate": 0.0, "ref_home_bias": 0.0, "ref_matches": 0.0, "ref_has_data": 0.0, "ref_strict": 0.0, "ref_lenient": 0.0}}, "xg_regression": {"probs": {"home": 0.421, "draw": 0.28, "away": 0.299}, "confidence": 0.189, "features": {"xgr_overperf_h": 0.434, "xgr_overperf_a": 0.729, "xgr_regression_h": -0.304, "xgr_regression_a": -0.511, "xgr_regression_diff": 0.207, "xgr_synth_xg_h": 0.766, "xgr_synth_xg_a": 1.271, "xgr_synth_xga_h": 0.847, "xgr_synth_xga_a": 0.633, "xgr_shot_quality_h": 0.706, "xgr_shot_quality_a": 0.645, "xgr_pyth_luck_h": 0.033, "xgr_pyth_luck_a": 0.028, "xgr_has_data": 1.0}}, "fbref_advanced": {"probs": {"home": 0.333, "draw": 0.27, "away": 0.397}, "confidence": 0.278, "features": {"fb_att_quality_h": 0.525, "fb_att_quality_a": 0.965, "fb_def_quality_h": 0.5, "fb_def_quality_a": 1.25, "fb_shot_quality_h": 0.615, "fb_shot_quality_a": 0.667, "fb_shot_accuracy_h": 0.277, "fb_shot_accuracy_a": 0.381, "fb_shot_volume_h": 5.875, "fb_shot_volume_a": 7.875, "fb_corner_dom_h": 0.571, "fb_corner_dom_a": 0.429, "fb_discipline_h": 1.0, "fb_discipline_a": 1.0, "fb_quality_mismatch": -1.19, "fb_has_data": 1.0, "fb_npxg_diff": 0.0, "fb_pass_accuracy_h": 0.0, "fb_pass_accuracy_a": 0.0, "fb_pressing_h": 0.0, "fb_pressing_a": 0.0, "fb_progressive_h": 0.0, "fb_progressive_a": 0.0, "fb_has_fbref": 0.0}}, "xpts": {"probs": {"home": 0.333, "draw": 0.333, "away": 0.333}, "confidence": 0.0, "features": {"xpts_home_luck": 0.0, "xpts_away_luck": 0.0, "xpts_home_ratio": 0.0, "xpts_away_ratio": 0.0, "xpts_luck_diff": 0.0, "xpts_regression_signal": 0.0, "xpts_has_data": 0.0, "xpts_overperformance": 0.0}}, "league_table": {"probs": {"home": 0.2, "draw": 0.36, "away": 0.44}, "confidence": 1.0, "features": {"lt_pos_h": 18.0, "lt_pos_a": 2.0, "lt_pos_diff": 16.0, "lt_rel_pos_h": 0.105, "lt_rel_pos_a": 0.947, "lt_ppg_h": 0.967, "lt_ppg_a": 2.033, "lt_ppg_diff": -1.067, "lt_gd_h": -19.0, "lt_gd_a": 32.0, "lt_gd_diff": -51.0, "lt_pts_h": 29.0, "lt_pts_a": 61.0, "lt_gap_top_h": 41.0, "lt_gap_top_a": 9.0, "lt_gap_bot_h": 12.0, "lt_gap_bot_a": 44.0, "lt_home_pos_h": 17.0, "lt_away_pos_a": 3.0, "lt_home_ppg_h": 0.867, "lt_away_ppg_a": 1.667, "lt_home_gd_h": -10.0, "lt_away_gd_a": 7.0, "lt_rel_zone_h": 1.0, "lt_rel_zone_a": 0.0, "lt_euro_zone_h": 0.0, "lt_euro_zone_a": 0.0, "lt_title_zone_h": 0.0, "lt_title_zone_a": 0.1, "lt_form_rel_h": 0.737, "lt_form_rel_a": 1.0, "lt_form_ppg_h": 1.5, "lt_form_ppg_a": 2.333, "lt_pos_form_gap_h": -0.632, "lt_pos_form_gap_a": -0.053}}, "seasonal_pattern": {"probs": {"home": 0.36, "draw": 0.28, "away": 0.36}, "confidence": 0.12, "features": {"sp_season_progress": 0.66, "sp_is_early": 0.0, "sp_is_late": 0.0, "sp_matchday_bucket": 1.0, "sp_month_sin": 0.866, "sp_month_cos": 0.5, "sp_phase_x_pos_h": -0.235, "sp_phase_x_pos_a": 0.235, "sp_fixture_congestion": 0.0}}, "venue": {"probs": {"home": 0.36, "draw": 0.28, "away": 0.36}, "confidence": 0.08, "features": {"venue_capacity": 0.0, "venue_altitude_m": NaN, "venue_travel_km": 0.0, "venue_is_synthetic": 0.0, "venue_has_data": 1.0, "venue_large_stadium": 0.0, "venue_high_altitude": 0.0, "venue_long_travel": 0.0}}, "pythagorean": {"probs": {"home": 0.333, "draw": 0.333, "away": 0.333}, "confidence": 0.85, "features": {"pyth_luck_h": 0.112, "pyth_luck_a": 0.114, "pyth_expected_ppg_h": 1.175, "pyth_expected_ppg_a": 1.808, "pyth_regression_signal": -0.001, "pyth_efficiency_h": 1.096, "pyth_efficiency_a": 1.063}}, "gas": {"probs": {"home": 0.046, "draw": 0.907, "away": 0.046}, "confidence": 0.85, "features": {"gas_strength_h": -8.909, "gas_strength_a": -12.866, "gas_diff": 3.957, "gas_home_adv": 0.25, "gas_volatility_h": 6.871, "gas_volatility_a": 7.838}}, "adaptive_bayesian": {"probs": {"home": 0.094, "draw": 0.441, "away": 0.465}, "confidence": 0.85, "features": {"abs_strength_h": 1.191, "abs_strength_a": 1.879, "abs_diff": -0.438, "abs_regime_h": 0.604, "abs_regime_a": 0.626, "abs_change_speed_h": 0.002, "abs_change_speed_a": 0.054, "abs_uncertainty_h": 0.128, "abs_uncertainty_a": 0.129}}, "hmm": {"probs": {"home": 0.343, "draw": 0.23, "away": 0.427}, "confidence": 0.85, "features": {"hmm_dominant_h": 0.311, "hmm_dominant_a": 0.407, "hmm_vulnerable_h": 0.266, "hmm_vulnerable_a": 0.154, "hmm_state_mismatch": -0.096, "hmm_transition_h": 0.335, "hmm_transition_a": 0.229}}, "transfer": {"probs": {"home": 0.333, "draw": 0.333, "away": 0.333}, "confidence": 0.0, "features": {"tf_value_change_h": 0.0, "tf_value_change_a": 0.0, "tf_squad_depth_h": 0.0, "tf_squad_depth_a": 0.0, "tf_age_profile_h": 0.0, "tf_age_profile_a": 0.0, "tf_integration_period": 0.0, "tf_depth_advantage": 0.0, "tf_value_dominance": 0.0}}, "news_sentiment": {"probs": {"home": 0.333, "draw": 0.333, "away": 0.333}, "confidence": 0.0, "features": {"ns_tone_h": 0.0, "ns_tone_a": 0.0, "ns_tone_diff": 0.0, "ns_volume_h": 0.0, "ns_volume_a": 0.0, "ns_disruption_h": 0.0, "ns_disruption_a": 0.0}}, "betting_movement": {"probs": {"home": 0.333, "draw": 0.333, "away": 0.333}, "confidence": 0.0, "features": {"bm_move_h": -0.019, "bm_move_d": 0.001, "bm_move_a": 0.018, "bm_magnitude": 0.038, "bm_direction_change": 0.0, "bm_late_shift": -0.012, "bm_sharp_signal": 0.0}}, "manager": {"probs": {"home": 0.537, "draw": 0.225, "away": 0.238}, "confidence": 0.217, "features": {"mgr_discontinuity_h": 0.0, "mgr_discontinuity_a": 0.222, "mgr_bounce_h": 0.0, "mgr_bounce_a": 0.222, "mgr_decline_h": 0.0, "mgr_decline_a": 0.0, "mgr_stability_h": 1.0, "mgr_stability_a": 0.778}}, "lineup": {"probs": {"home": 0.351, "draw": 0.28, "away": 0.369}, "confidence": 0.172, "features": {"lu_formation_change_h": 0.0, "lu_formation_change_a": 0.0, "lu_squad_strength_h": 0.872, "lu_squad_strength_a": 0.958, "lu_availability_h": 0.96, "lu_availability_a": 1.16, "lu_rotation_risk_h": 1.0, "lu_rotation_risk_a": 1.0}}, "match_dynamics": {"probs": {"home": 0.333, "draw": 0.333, "away": 0.333}, "confidence": 0.85, "features": {"md_comeback_h": 0.078, "md_comeback_a": 0.101, "md_collapse_h": 0.097, "md_collapse_a": 0.051, "md_ht_draw_win_h": 0.286, "md_ht_draw_win_a": 0.46, "md_set_piece_dep_h": 0.294, "md_set_piece_dep_a": 0.2, "md_card_rate_h": NaN, "md_card_rate_a": NaN, "md_streak_h": 2.0, "md_streak_a": 0.0, "md_streak_break_h": 0.19, "md_streak_break_a": 0.0, "md_resilience_h": 0.245, "md_resilience_a": 0.262}}, "schedule_context": {"probs": {"home": 0.353, "draw": 0.294, "away": 0.353}, "confidence": 0.1, "features": {"sc_midweek_fatigue_h": 0.0, "sc_midweek_fatigue_a": 0.0, "sc_post_intl_break": 1.0, "sc_promoted_honeymoon_h": 0.0, "sc_promoted_honeymoon_a": 0.0, "sc_holiday_congestion": 0.0, "sc_dead_rubber_h": 0.0, "sc_dead_rubber_a": 0.0, "sc_opening_day": 0.0, "sc_schedule_advantage": 0.0}}, "opponent_adjusted": {"probs": {"home": 0.319, "draw": 0.28, "away": 0.401}, "confidence": 0.85, "features": {"oa_ppg_h": 1.384, "oa_ppg_a": 1.896, "oa_gf_h": 1.409, "oa_gf_a": 1.589, "oa_ga_h": 1.618, "oa_ga_a": 1.003, "oa_strength_diff": -0.512, "ppda_h": 0.0, "ppda_a": 0.0, "style_set_piece_h": 0.089, "style_set_piece_a": 0.079, "pts_to_safety_h": 1003.0, "pts_to_safety_a": 1722.0, "pts_to_title_h": 848.0, "pts_to_title_a": 129.0, "post_intl_record_h": 2.0, "post_intl_record_a": 2.0}}, "trueskill": {"probs": {"home": 0.501, "draw": 0.185, "away": 0.314}, "confidence": 0.845, "features": {"ts_skill_diff": 333.882, "ts_attack_diff": 166.941, "ts_defense_diff": -166.941, "ts_uncertainty": 183.498, "ts_confidence": 0.845, "ts_momentum_h": 1.579, "ts_momentum_a": -0.97, "ts_home_adv": 0.883}}}}