{"match_id": 8494324491738221883, "home_team": "Sporting Charleroi", "away_team": "OH Leuven", "utc_date": "2026-03-14 00:00", "competition": "BEL", "status": "SCHEDULED", "home_goals": null, "away_goals": null, "prediction": {"p_home": 0.802, "p_draw": 0.128, "p_away": 0.07, "eg_home": 2.02, "eg_away": 0.88}, "poisson": {"btts": 0.482, "o25": 0.574, "predicted_score": [3, 1], "lambda_home": 3.35, "lambda_away": 1.01}, "odds": null, "elo": {"home": 1495.0, "away": 1516.0, "diff": -21.0}, "score": null}