{"stats": {"total_matches": 25, "team_a_wins": 7, "team_b_wins": 10, "draws": 8, "team_a": "Auxerre", "team_b": "Monaco", "team_a_avg_goals_for": 1.08, "team_a_avg_goals_against": 1.32, "team_b_avg_goals_for": 1.32, "team_b_avg_goals_against": 1.08}, "recent_matches": [{"utc_date": "2025-09-13", "home_team": "Auxerre", "away_team": "Monaco", "home_goals": 1, "away_goals": 2}, {"utc_date": "2025-09-13", "home_team": "Auxerre", "away_team": "Monaco", "home_goals": 1, "away_goals": 2}, {"utc_date": "2025-02-01", "home_team": "Monaco", "away_team": "Auxerre", "home_goals": 4, "away_goals": 2}, {"utc_date": "2024-09-14", "home_team": "Auxerre", "away_team": "Monaco", "home_goals": 0, "away_goals": 3}, {"utc_date": "2023-02-01", "home_team": "Monaco", "away_team": "Auxerre", "home_goals": 3, "away_goals": 2}, {"utc_date": "2022-12-28", "home_team": "Auxerre", "away_team": "Monaco", "home_goals": 2, "away_goals": 3}, {"utc_date": "2011-01-15", "home_team": "Auxerre", "away_team": "Monaco", "home_goals": 1, "away_goals": 1}, {"utc_date": "2010-08-29", "home_team": "Monaco", "away_team": "Auxerre", "home_goals": 2, "away_goals": 0}, {"utc_date": "2010-03-29", "home_team": "Monaco", "away_team": "Auxerre", "home_goals": 0, "away_goals": 0}, {"utc_date": "2009-11-21", "home_team": "Auxerre", "away_team": "Monaco", "home_goals": 2, "away_goals": 0}]}