{"standings": [{"team": "Arsenal", "p": 52, "w": 34, "d": 12, "l": 6, "gf": 100, "ga": 36, "pts": 114, "pos": 1, "gd": 64}, {"team": "Manchester City", "p": 52, "w": 32, "d": 10, "l": 10, "gf": 108, "ga": 48, "pts": 106, "pos": 2, "gd": 60}, {"team": "Aston Villa", "p": 52, "w": 30, "d": 10, "l": 12, "gf": 74, "ga": 54, "pts": 100, "pos": 3, "gd": 20}, {"team": "Manchester United", "p": 52, "w": 24, "d": 18, "l": 10, "gf": 94, "ga": 74, "pts": 90, "pos": 4, "gd": 20}, {"team": "Chelsea", "p": 52, "w": 24, "d": 16, "l": 12, "gf": 94, "ga": 60, "pts": 88, "pos": 5, "gd": 34}, {"team": "Liverpool", "p": 52, "w": 24, "d": 12, "l": 16, "gf": 82, "ga": 70, "pts": 84, "pos": 6, "gd": 12}, {"team": "Brentford", "p": 52, "w": 24, "d": 8, "l": 20, "gf": 80, "ga": 70, "pts": 80, "pos": 7, "gd": 10}, {"team": "Everton", "p": 52, "w": 20, "d": 14, "l": 18, "gf": 58, "ga": 60, "pts": 74, "pos": 8, "gd": -2}, {"team": "Bournemouth", "p": 52, "w": 18, "d": 20, "l": 14, "gf": 86, "ga": 90, "pts": 74, "pos": 9, "gd": -4}, {"team": "Newcastle United", "p": 52, "w": 20, "d": 12, "l": 20, "gf": 74, "ga": 74, "pts": 72, "pos": 10, "gd": 0}, {"team": "Sunderland", "p": 52, "w": 18, "d": 18, "l": 16, "gf": 54, "ga": 60, "pts": 72, "pos": 11, "gd": -6}, {"team": "Fulham", "p": 52, "w": 20, "d": 8, "l": 24, "gf": 70, "ga": 80, "pts": 68, "pos": 12, "gd": -10}, {"team": "Crystal Palace", "p": 52, "w": 16, "d": 16, "l": 20, "gf": 56, "ga": 64, "pts": 64, "pos": 13, "gd": -8}, {"team": "Brighton", "p": 52, "w": 14, "d": 20, "l": 18, "gf": 68, "ga": 68, "pts": 62, "pos": 14, "gd": 0}, {"team": "Leeds United", "p": 52, "w": 14, "d": 18, "l": 20, "gf": 72, "ga": 90, "pts": 60, "pos": 15, "gd": -18}, {"team": "Tottenham Hotspur", "p": 52, "w": 14, "d": 16, "l": 22, "gf": 72, "ga": 74, "pts": 58, "pos": 16, "gd": -2}, {"team": "Nottingham Forest", "p": 52, "w": 14, "d": 12, "l": 26, "gf": 50, "ga": 76, "pts": 54, "pos": 17, "gd": -26}, {"team": "West Ham", "p": 52, "w": 12, "d": 12, "l": 28, "gf": 64, "ga": 98, "pts": 48, "pos": 18, "gd": -34}, {"team": "Burnley", "p": 52, "w": 8, "d": 12, "l": 32, "gf": 56, "ga": 102, "pts": 36, "pos": 19, "gd": -46}, {"team": "Wolverhampton Wanderers", "p": 52, "w": 2, "d": 12, "l": 38, "gf": 32, "ga": 96, "pts": 18, "pos": 20, "gd": -64}]}